virgosuite/__init__.py
virgosuite/global_settings.py
virgosuite/storage_manager.py
virgosuite/time_series.py
virgosuite/analisys/__init__.py
virgosuite/analisys/generator/__init__.py
virgosuite/analisys/generator/random.py
virgosuite-1.3.23.dist-info/LICENSE.txt
virgosuite-1.3.23.dist-info/METADATA
virgosuite-1.3.23.dist-info/WHEEL
virgosuite-1.3.23.dist-info/top_level.txt
virgosuite-1.3.23.dist-info/RECORD
