Metadata-Version: 2.1
Name: virgosuite
Version: 1.3.23
Summary: Toolbox used from the data analysis group of Virgo Rome
Author: Riccardo Felicetti
Author-email: riccardo.felicetti@infn.it
License: MIT
Classifier: Development Status :: 3 - Alpha
License-File: LICENSE.txt
Requires-Dist: numpy
Requires-Dist: scipy
Requires-Dist: matplotlib
Requires-Dist: pandas
Requires-Dist: h5py
Requires-Dist: dask
Requires-Dist: astropy
Requires-Dist: xarray
Requires-Dist: pyarrow
Requires-Dist: dask[diagnostics]
Requires-Dist: polars
